setup.py
butter_cli.egg-info/PKG-INFO
butter_cli.egg-info/SOURCES.txt
butter_cli.egg-info/dependency_links.txt
butter_cli.egg-info/requires.txt
butter_cli.egg-info/top_level.txt
src/butter/__init__.py
src/butter/butter.py
src/butter/cli.py
src/butter_cli.egg-info/PKG-INFO
src/butter_cli.egg-info/SOURCES.txt
src/butter_cli.egg-info/dependency_links.txt
src/butter_cli.egg-info/entry_points.txt
src/butter_cli.egg-info/requires.txt
src/butter_cli.egg-info/top_level.txt