Metadata-Version: 2.1
Name: butter-cli
Version: 1.11
Summary: CI/CD for generative AI
Home-page: https://github.com/Michael-Equi/butter
Author: Michael Equi
Author-email: michaelequi@berkeley.edu
